<?xml version="1.0" encoding="UTF-8" ?>
<!DOCTYPE tiles-definitions PUBLIC
"-//Apache Software Foundation//DTD Tiles Configuration 2.0//EN"
"http://tiles.apache.org/dtds/tiles-config_2_0.dtd">
<tiles-definitions>
    <!-- Basis layout -->
    <definition name="baseLayout" template="/WEB-INF/tiles/BaseLayout.jsp">
        <put-attribute name="title" value="" />
        <put-attribute name="header" value="/WEB-INF/tiles/header.jsp" />
        <put-attribute name="menu" value="/WEB-INF/tiles/navigation.jsp" />
        <put-attribute name="body" value="" />
        <put-attribute name="footer" value="/WEB-INF/tiles/footer.jsp" />
    </definition>
    <!--Webpage Root-->
    <definition name="index" extends="baseLayout">
        <put-attribute name="title" value="omicsFusion" />
        <put-attribute name="body" value="/WEB-INF/webPages/index_body.jsp" />
    </definition>
    <definition name="todo" extends="baseLayout">
        <put-attribute name="title" value="todo list" />
        <put-attribute name="body" value="/WEB-INF/webPages/results/todo_body.jsp" />
    </definition>
    <!--Error Pages-->
    <definition name="403" extends="baseLayout">
        <put-attribute name="title" value="403 - Not authorized" />
        <put-attribute name="body" value="/WEB-INF/webPages/errorPages/403_body.jsp" />
    </definition>
    <definition name="404" extends="baseLayout">
        <put-attribute name="title" value="404 - Not found" />
        <put-attribute name="body" value="/WEB-INF/webPages/errorPages/404_body.jsp" />
    </definition>
    <definition name="500" extends="baseLayout">
        <put-attribute name="title" value="500 - Internal server error" />
        <put-attribute name="body" value="/WEB-INF/webPages/errorPages/500_body.jsp" />
    </definition>
    <!--Submit wizard-->
    <definition name="submitIndex" extends="baseLayout">
        <put-attribute name="title" value="omicsFusion" />
        <put-attribute name="body" value="/WEB-INF/webPages/submit/index_body.jsp" />
    </definition>
    <definition name="methodSelection" extends="baseLayout">
        <put-attribute name="title" value="omicsFusion" />
        <put-attribute name="body" value="/WEB-INF/webPages/submit/methodSelection_body.jsp" />
    </definition>
    <definition name="uploadExcel" extends="baseLayout">
        <put-attribute name="title" value="omicsFusion" />
        <put-attribute name="body" value="/WEB-INF/webPages/submit/uploadExcel_body.jsp" />
    </definition>
    <definition name="userDetails" extends="baseLayout">
        <put-attribute name="title" value="omicsFusion" />
        <put-attribute name="body" value="/WEB-INF/webPages/submit/userDetails_body.jsp" />
    </definition>
    <definition name="wizardComplete" extends="baseLayout">
        <put-attribute name="title" value="omicsFusion" />
        <put-attribute name="body" value="/WEB-INF/webPages/submit/wizardComplete_body.jsp" />
    </definition>
    <definition name="run" extends="baseLayout">
        <put-attribute name="title" value="omicsFusion" />
        <put-attribute name="body" value="/WEB-INF/webPages/submit/run_body.jsp" />
    </definition>
    <definition name="wait" extends="baseLayout">
        <put-attribute name="title" value="Please wait" />
        <put-attribute name="body" value="/WEB-INF/webPages/submit/wait_body.jsp" />
    </definition>
    <!-- View results -->
    <definition name="resultsIndex" extends="baseLayout">
        <put-attribute name="title" value="omicsFusion" />
        <put-attribute name="body" value="/WEB-INF/webPages/results/index_body.jsp" />
    </definition>
</tiles-definitions>